ascii_youtube/__init__.py
ascii_youtube/ascii_frames.py
ascii_youtube/cli.py
ascii_youtube/play.py
ascii_yt-2.1.1.dist-info/LICENSE
ascii_yt-2.1.1.dist-info/METADATA
ascii_yt-2.1.1.dist-info/WHEEL
ascii_yt-2.1.1.dist-info/entry_points.txt
ascii_yt-2.1.1.dist-info/top_level.txt
ascii_yt-2.1.1.dist-info/RECORD
