Metadata-Version: 2.1
Name: ascii-yt
Version: 2.1.1
Summary: play any youtube video ▶ with ASCII in the terminal.
Home-page: https://github.com/malkiii/ascii-yt
Author: Malki Abdurrahman
Project-URL: Source, https://github.com/malkiii/ascii-yt
Project-URL: Tracker, https://github.com/malkiii/ascii-yt/issues
Keywords: ascii,art,video,youtube,linux,shell,python,terminal
Classifier: License :: OSI Approved :: MIT License
Classifier: Intended Audience :: Developers
Classifier: Operating System :: OS Independent
Classifier: Programming Language :: Python :: 3
Classifier: Programming Language :: Python :: 3.10
License-File: LICENSE
Requires-Dist: opencv-python (==4.7.0.68)
Requires-Dist: cap-from-youtube
